autolist/__init__.py
autolist/correctlist.py
autolist/corrector.py
autolist-0.0.5.dist-info/LICENSE
autolist-0.0.5.dist-info/METADATA
autolist-0.0.5.dist-info/WHEEL
autolist-0.0.5.dist-info/top_level.txt
autolist-0.0.5.dist-info/RECORD
