Metadata-Version: 2.1
Name: autolist
Version: 0.0.5
Summary: Auto-Corrects mistyped words by checking them with the list of given correct words
Home-page: https://github.com/AbelR007/Autolist
Author: Abel Roy
Author-email: abelroi007@gmail.com
License: UNKNOWN
Platform: UNKNOWN
Classifier: Programming Language :: Python :: 3
Classifier: License :: OSI Approved :: MIT License
Classifier: Operating System :: OS Independent
License-File: LICENSE
